{"expireTime":9007200872344055000,"key":"contentful-sync-data-84mtkp5mehak-master","val":{"entries":[{"metadata":{"tags":[]},"sys":{"space":{"sys":{"type":"Link","linkType":"Space","id":"84mtkp5mehak"}},"id":"7HzHxx6F3lPltoZzftXjL4","type":"Entry","createdAt":"2021-04-05T05:58:58.049Z","updatedAt":"2021-04-05T05:58:58.049Z","environment":{"sys":{"id":"master","type":"Link","linkType":"Environment"}},"revision":1,"contentType":{"sys":{"type":"Link","linkType":"ContentType","id":"work"}}},"fields":{"title":{"en-US":"Shopify"},"summary":{"en-US":"SHopify + contentful"},"content":{"en-US":"# 連携\n\n### shopify + contentful\n"}}}],"assets":[]}}